{
  "project_info": {
    "project_number": "1088101595044",
    "firebase_url": "https://fitness-enthusiasts-default-rtdb.firebaseio.com",
    "project_id": "fitness-enthusiasts",
    "storage_bucket": "fitness-enthusiasts.appspot.com"
  },
  "client": [
    {
      "client_info": {
        "mobilesdk_app_id": "1:1088101595044:android:0e079b8e003458496ab331",
        "android_client_info": {
          "package_name": "com.example.fitnessenthusiasts"
        }
      },
      "oauth_client": [
        {
          "client_id": "1088101595044-1qkvfg6ohf3k025ts4pioi0kp8md6qnb.apps.googleusercontent.com",
          "client_type": 3
        }
      ],
      "api_key": [
        {
          "current_key": "AIzaSyC4uEfLr922HcFARPLzcGmrVP9TYxiG3m8"
        }
      ],
      "services": {
        "appinvite_service": {
          "other_platform_oauth_client": [
            {
              "client_id": "1088101595044-1qkvfg6ohf3k025ts4pioi0kp8md6qnb.apps.googleusercontent.com",
              "client_type": 3
            }
          ]
        }
      }
    }
  ],
  "configuration_version": "1"
}